htlfc/ABOUT.md
htlfc/VERSION
htlfc/__init__.py
htlfc/main.py
htlfc/version.py
htlfc/agents/__init__.py
htlfc/agents/codecs.py
htlfc/agents/filedir.py
htlfc/agents/loader.py
htlfc/agents/maff.py
htlfc/agents/mht.py
htlfc/agents/war.py
htlfc/gui/__init__.py
htlfc/gui/converter.py
htlfc/gui/find.py
htlfc/gui/interface.py
htlfc/gui/select.py
htlfc/gui/viewer.py
htlfc/merger/__init__.py
htlfc/merger/convert.py
htlfc/merger/infobar.css
htlfc/merger/manifest.py
htlfc/merger/xmltree.py
htlfc-0.5.1.dist-info/LICENSE
htlfc-0.5.1.dist-info/METADATA
htlfc-0.5.1.dist-info/WHEEL
htlfc-0.5.1.dist-info/entry_points.txt
htlfc-0.5.1.dist-info/top_level.txt
htlfc-0.5.1.dist-info/RECORD
