Metadata-Version: 2.1
Name: htlfc
Version: 0.5.1
Summary: Hypertext Legacy File Converter
License: AGPLv3+
Keywords: hypertext,html,mht,mhtml,maff
Classifier: Intended Audience :: End Users/Desktop
Classifier: Programming Language :: Python :: 3.6
Classifier: License :: OSI Approved :: GNU Affero General Public License v3 or later (AGPLv3+)
Classifier: Operating System :: OS Independent
Classifier: Topic :: Internet :: WWW/HTTP :: Browsers
Requires-Python: >=3.7
License-File: LICENSE
Requires-Dist: lxml
Requires-Dist: chardet
